{
    "description": "",
    "tags": [],
    "size": {
        "height": 185,
        "width": 400
    },
    "objects": [
        {
            "id": 6325334,
            "classId": 8709,
            "description": "",
            "geometryType": "rectangle",
            "labelerLogin": "az@datasetninja.com",
            "createdAt": "2023-06-13T22:39:10.061Z",
            "updatedAt": "2023-06-13T22:39:10.061Z",
            "tags": [],
            "classTitle": "license plate",
            "points": {
                "exterior": [
                    [
                        42,
                        126
                    ],
                    [
                        86,
                        137
                    ]
                ],
                "interior": []
            }
        }
    ]
}