{
    "description": "",
    "tags": [],
    "size": {
        "height": 229,
        "width": 558
    },
    "objects": [
        {
            "id": 6325299,
            "classId": 8709,
            "description": "",
            "geometryType": "rectangle",
            "labelerLogin": "az@datasetninja.com",
            "createdAt": "2023-06-13T22:38:53.150Z",
            "updatedAt": "2023-06-13T22:38:53.150Z",
            "tags": [],
            "classTitle": "license plate",
            "points": {
                "exterior": [
                    [
                        170,
                        81
                    ],
                    [
                        316,
                        121
                    ]
                ],
                "interior": []
            }
        }
    ]
}